{"cameraMode":{"drawMode":0,"name":"Shaded","section":"Shading Mode"},"sceneLighting":true,"audioPlay":false,"sceneViewState":{"showFog":true,"showMaterialUpdate":false,"showSkybox":true,"showFlares":true,"showImageEffects":true,"showParticleSystems":true},"in2DMode":false,"pivot":{"x":-41.64726638793945,"y":2.362062931060791,"z":-72.99264526367188},"rotation":{"x":-0.05932149291038513,"y":-0.3468136787414551,"z":0.021999863907694818,"w":-0.9358291029930115},"size":2.9142909049987795,"orthographic":false}